MANIFEST.in
Pipfile
Pipfile.lock
README.md
setup.cfg
setup.py
tox.ini
impbus/__init__.py
impbus/__version__.py
impbus/imp_bus.py
impbus/imp_commands.py
impbus/imp_crc.py
impbus/imp_datatypes.py
impbus/imp_device.py
impbus/imp_eeprom.py
impbus/imp_errors.json
impbus/imp_errors.py
impbus/imp_helper.py
impbus/imp_modules.py
impbus/imp_packages.py
impbus/imp_responces.py
impbus/imp_tables.json
impbus/imp_tables.py
impbus.egg-info/PKG-INFO
impbus.egg-info/SOURCES.txt
impbus.egg-info/dependency_links.txt
impbus.egg-info/requires.txt
impbus.egg-info/top_level.txt
tests/__init__.py
tests/test_bus.py
tests/test_commands.py
tests/test_crc.py
tests/test_datatypes.py
tests/test_device.py
tests/test_eeprom.py
tests/test_errors.json
tests/test_errors.py
tests/test_helper.py
tests/test_modules.py
tests/test_packages.py
tests/test_responces.py
tests/test_tables.json
tests/test_tables.py
tests/test_version.py